superfunctions_sqlalchemy/__init__.py
superfunctions_sqlalchemy/adapter.py
superfunctions_sqlalchemy-0.1.0.dist-info/METADATA
superfunctions_sqlalchemy-0.1.0.dist-info/WHEEL
superfunctions_sqlalchemy-0.1.0.dist-info/RECORD
