Metadata-Version: 2.4
Name: superfunctions-sqlalchemy
Version: 0.1.0
Summary: SQLAlchemy adapter for superfunctions.db
Project-URL: Documentation, https://docs.superfunctions.dev/adapters/sqlalchemy
Project-URL: Repository, https://github.com/21nCo/super-functions
Project-URL: Issues, https://github.com/21nCo/super-functions/issues
Author-email: 21n <support@superfunctions.dev>
License-Expression: MIT
Keywords: adapter,database,orm,sqlalchemy,superfunctions
Classifier: Development Status :: 3 - Alpha
Classifier: Intended Audience :: Developers
Classifier: License :: OSI Approved :: MIT License
Classifier: Programming Language :: Python :: 3
Classifier: Programming Language :: Python :: 3.10
Classifier: Programming Language :: Python :: 3.11
Classifier: Programming Language :: Python :: 3.12
Classifier: Topic :: Database
Classifier: Topic :: Software Development :: Libraries :: Python Modules
Requires-Python: >=3.10
Requires-Dist: sqlalchemy>=2.0.0
Requires-Dist: superfunctions>=0.1.0
Provides-Extra: asyncpg
Requires-Dist: asyncpg>=0.29.0; extra == 'asyncpg'
Provides-Extra: dev
Requires-Dist: mypy>=1.7.0; extra == 'dev'
Requires-Dist: pytest-asyncio>=0.21.0; extra == 'dev'
Requires-Dist: pytest>=7.4.0; extra == 'dev'
Requires-Dist: ruff>=0.1.6; extra == 'dev'
Provides-Extra: mysql
Requires-Dist: pymysql>=1.1.0; extra == 'mysql'
Provides-Extra: postgres
Requires-Dist: psycopg2-binary>=2.9.0; extra == 'postgres'
Provides-Extra: sqlite
